[
	{
		"Name":"圆柱(标)",
		"ImagePath":"YuanZhu.png",
		"Type":0,
		"IdSuffix":"_YuanZhuParamDesignPanel.json"
	},
	{
		"Name":"长方体(标)",
		"ImagePath":"ChangFangTi.png",
		"Type":0,
		"IdSuffix":"_ChangFangTiParamDesignPanel.json"
	},
	{
		"Name":"框体(标)",
		"ImagePath":"KuangTi.png",
		"Type":0,
		"IdSuffix":"_KuangTiParamDesignPanel.json"
	},
	{
		"Name":"球体(标)",
		"ImagePath":"QiuTi.png",
		"Type":0,
		"IdSuffix":"_QiuTiParamDesignPanel.json"
	},
	{
		"Name":"圆柱+圆柱(变)",
		"ImagePath":"YuanZhuYuanZhu.png",
		"Type":0,
		"IdSuffix":"_YuanZhu2ParamDesignPanel.json"
	},
	{
		"Name":"长方体+圆柱(变)",
		"ImagePath":"ChangFangTiYuanZhu.png",
		"Type":0,
		"IdSuffix":"_ChangFangTiYuanZhuParamDesignPanel.json"
	},
	{
		"Name":"框体+圆柱(变)",
		"ImagePath":"KuangTiYuanZhu.png",
		"Type":0,
		"IdSuffix":"_KuangTiYuanZhuParamDesignPanel.json"
	},
	{
		"Name":"入口面",
		"ImagePath":"YuanZhu.png",
		"Type":1,
		"IdSuffix":"_RuKouMianParamDesignPanel.json"
	},
	{
		"Name":"出口面",
		"ImagePath":"YuanZhu.png",
		"Type":1,
		"IdSuffix":"_ChuKouMianParamDesignPanel.json"
	},
	{
		"Name":"中间状态",
		"ImagePath":"YuanZhu.png",
		"Type":1,
		"IdSuffix":"_ZhongJianZhuangTaiParamDesignPanel.json"
	},
	{
		"Name":"定位面",
		"ImagePath":"YuanZhu.png",
		"Type":1,
		"IdSuffix":"_DingWeiMianParamDesignPanel.json"
	},
	{
		"Name":"孔底面",
		"ImagePath":"YuanZhu.png",
		"Type":1,
		"IdSuffix":"_KongDiMianParamDesignPanel.json"
	},
	{
		"Name":"内倒角",
		"ImagePath":"YuanZhu.png",
		"Type":2,
		"IdSuffix":"_NeiDaoJiaoParamDesignPanel.json"
	},
	{
		"Name":"外倒角",
		"ImagePath":"YuanZhu.png",
		"Type":2,
		"IdSuffix":"_WaiDaoJiaoParamDesignPanel.json"
	},
	{
		"Name":"反倒角",
		"ImagePath":"YuanZhu.png",
		"Type":2,
		"IdSuffix":"_FanDaoJiaoParamDesignPanel.json"
	},
	{
		"Name":"孔",
		"ImagePath":"YuanZhu.png",
		"Type":2,
		"IdSuffix":"_TongKongParamDesignPanel.json"
	},
	{
		"Name":"盲孔",
		"ImagePath":"YuanZhu.png",
		"Type":2,
		"IdSuffix":"_MangKong"
	},
	{
		"Name":"通孔",
		"ImagePath":"YuanZhu.png",
		"Type":2,
		"IdSuffix":"_TongKongParamDesignPanel.json"
	},
	{
		"Name":"中间孔相贯",
		"ImagePath":"YuanZhu.png",
		"Type":2,
		"IdSuffix":"_ZhongJianKongXiangGuanParamDesignPanel.json"
	},
	{
		"Name":"中间状态",
		"ImagePath":"YuanZhu.png",
		"Type":2,
		"IdSuffix":"_ZhongJianZhuangTaiParamDesignPanel.json"
	},
	{
		"Name":"內倒圆",
		"ImagePath":"YuanZhu.png",
		"Type":2,
		"IdSuffix":"_NeiDaoYuanParamDesignPanel.json"
	},
	{
		"Name":"外倒圆",
		"ImagePath":"YuanZhu.png",
		"Type":2,
		"IdSuffix":"_WaiDaoYuanParamDesignPanel.json"
	},
	{
		"Name":"内锥面",
		"ImagePath":"YuanZhu.png",
		"Type":2,
		"IdSuffix":"_NeiZhuiMianParamDesignPanel.json"
	},
	{
		"Name":"外锥面",
		"ImagePath":"YuanZhu.png",
		"Type":2,
		"IdSuffix":"_WaiZhuiMianParamDesignPanel.json"
	},
	{
		"Name":"内螺纹",
		"ImagePath":"YuanZhu.png",
		"Type":3,
		"IdSuffix":"_NeiLuoWenParamDesignPanel.json"
	},
	{
		"Name":"外螺纹",
		"ImagePath":"YuanZhu.png",
		"Type":3,
		"IdSuffix":"_WaiLuoWenParamDesignPanel.json"
	},
	{
		"Name":"端面方槽",
		"ImagePath":"YuanZhu.png",
		"Type":3,
		"IdSuffix":"_DuanMianFangCaoParamDesignPanel.json"
	},
	{
		"Name":"内方槽",
		"ImagePath":"YuanZhu.png",
		"Type":3,
		"IdSuffix":"_NeiFangCaoParamDesignPanel.json"
	},
	{
		"Name":"端面圆槽",
		"ImagePath":"YuanZhu.png",
		"Type":3,
		"IdSuffix":"_DuanMianYuanCaoParamDesignPanel.json"
	},
	{
		"Name":"内圆槽",
		"ImagePath":"YuanZhu.png",
		"Type":3,
		"IdSuffix":"_NeiYuanCaoParamDesignPanel.json"
	},
	{
		"Name":"外方槽",
		"ImagePath":"YuanZhu.png",
		"Type":3,
		"IdSuffix":"_WaiFangCaoParamDesignPanel.json"
	},
	{
		"Name": "外圆槽",
		"ImagePath": "YuanZhu.png",
		"Type": 3,
		"IdSuffix":"_WaiYuanCaoParamDesignPanel.json"
	},
	{
		"Name": "夹具零件干涉尺寸",
		"ImagePath": "YuanZhu.png",
		"Type": 4,
		"IdSuffix":"_JiaJuLingJianGanSheChiCunParamDesignPanel.json"
	}
]